CHANGELOG.md
LICENSE
MANIFEST.in
README.md
demo.md
requirements-dev.txt
requirements.txt
setup.cfg
setup.py
world_trade_data/__init__.py
world_trade_data/data.py
world_trade_data/defaults.py
world_trade_data/referential.py
world_trade_data/version.py
world_trade_data.egg-info/PKG-INFO
world_trade_data.egg-info/SOURCES.txt
world_trade_data.egg-info/dependency_links.txt
world_trade_data.egg-info/requires.txt
world_trade_data.egg-info/top_level.txt